{"Book":[
    {"title":"XML and Web Technologies for Data Sciences with R", "author":"Deborah Nolan", "publisher":"Springer", "isbn":"978-1-4614-7899-7", "subject":"R"}, 
    {"title":"Probability With Application and R", "author":"Robert P. Dobrow", "publisher":"Springer", "isbn":"978-1-4614-7899-7", "subject":"R"},
    {"title":"XML and Web Technologies for Data Sciences with R", "author":"Duncan Temple Lang", "publisher":"Springer", "isbn":"978-1-4614-7899-7", "subject":"R"},
    {"title":"Mathematical Statictics With Resampling and R", "author":"Laura Chihara", "publisher":"Wiley", "isbn":"978-1-118-02985-5", "subject":"R"},
    {"title":"Mathematical Statictics With Resampling and R", "author":"Tim Hesterberg", "publisher":"Wiley", "isbn":"978-1-118-02985-5", "subject":"R"}
]}
